[{"active_video_filename": {"id": 40139, "length": 1915, "video_filename_type": {"id": 3, "value": "archived"}}, "content_code": "sm5YoTCQouoWVhQvUzbzF8gQ", "display_date": "2023-08-15 07:04:17", "live_finished_at": "2023-08-15 07:04:17", "released_at": "2023-08-15 06:26:16", "start_with_free_part_flg": true, "thumbnail_url": "https://cdn.nicochannel.jp/public_html/contents/video_pages/17631/thumbnail_path?time=1692161122", "title": "\u3010\u30a8\u30c1\u30a8\u30c1\u751f\u653e\u9001#9\u3011\u4e08\u77ed\u3081\u6d74\u8863\u30b3\u30b9\u30d7\u30ec\u3067\u2026\ud83d\udc58\ud83d\udc95", "type": "vod", "user_video_play_history": null, "video_aggregate_info": {"id": 114299817, "number_of_comments": 2, "total_views": 3609}, "video_comment_setting": {"allow_comment_flg": false, "disp_main_comment_flg": false, "disp_number_of_comment_flg": false, "disp_number_of_views_flg": false, "disp_rightside_comment_flg": false}, "video_delivery_target": {"id": 3}, "video_free_periods": [{"elapsed_ended_time": 5, "elapsed_started_time": 0, "id": 13254}], "video_media_type": {"id": 1, "status": "movie"}}]