[{"active_video_filename": {"id": 84949, "length": 3809, "video_filename_type": {"id": 1, "value": "vod_origin"}}, "content_code": "smX7Vm7bLNCSiKmraSz52hp2", "display_date": "2024-07-19 05:06:13", "live_finished_at": null, "released_at": "2024-07-19 05:06:13", "start_with_free_part_flg": false, "thumbnail_url": "https://cdn.nicochannel.jp/public_html/contents/video_pages/34858/thumbnail_path?time=1721446294", "title": "\u3010\u8033\u8210\u3081ASMR\u3011\u5927\u4e08\u592b\u2661\u6016\u304f\u306a\u3044\u304b\u3089\u306d\u2026\u3010\u5927\u5bb6\u3061\u3072\u308d/Vtuber\u3011", "type": "vod", "user_video_play_history": null, "video_aggregate_info": {"id": 221867478, "number_of_comments": 0, "total_views": 3531}, "video_comment_setting": {"allow_comment_flg": true, "disp_main_comment_flg": true, "disp_number_of_comment_flg": true, "disp_number_of_views_flg": true, "disp_rightside_comment_flg": true}, "video_delivery_target": {"id": 2}, "video_free_periods": [], "video_media_type": {"id": 1, "status": "movie"}}, {"active_video_filename": {"id": 84946, "length": 3700, "video_filename_type": {"id": 1, "value": "vod_origin"}}, "content_code": "smjyESu55hS7JqrZKFUE2sQp", "display_date": "2024-07-19 05:04:42", "live_finished_at": null, "released_at": "2024-07-19 05:04:42", "start_with_free_part_flg": false, "thumbnail_url": "https://cdn.nicochannel.jp/public_html/contents/video_pages/34857/thumbnail_path?time=1721365484", "title": "\u3010\u8033\u8210\u3081ASMR\u3011\u304a\u8033\u304b\u3089\u6e29\u307e\u3063\u3066\u30ea\u30e9\u30c3\u30af\u30b9\u3067\u304d\u3061\u3083\u3046\u2661\u3010\u5927\u5bb6\u3061\u3072\u308d/Vtuber\u3011", "type": "vod", "user_video_play_history": null, "video_aggregate_info": {"id": 221942172, "number_of_comments": 0, "total_views": 2191}, "video_comment_setting": {"allow_comment_flg": true, "disp_main_comment_flg": true, "disp_number_of_comment_flg": true, "disp_number_of_views_flg": true, "disp_rightside_comment_flg": true}, "video_delivery_target": {"id": 2}, "video_free_periods": [], "video_media_type": {"id": 1, "status": "movie"}}, {"active_video_filename": {"id": 84940, "length": 3713, "video_filename_type": {"id": 1, "value": "vod_origin"}}, "content_code": "smX3QybP6swx7pcrzrshxpgn", "display_date": "2024-07-19 05:03:17", "live_finished_at": null, "released_at": "2024-07-19 05:03:17", "start_with_free_part_flg": false, "thumbnail_url": "https://cdn.nicochannel.jp/public_html/contents/video_pages/34856/thumbnail_path?time=1721365399", "title": "\u518d\u751f\u56de\u657010\u4e07\u8d85\u2661\u3010\u8033\u8210\u3081ASMR\u3011\u4eca\u65e5\u306f\u9003\u304c\u3057\u3066\u3042\u3052\u307e\u305b\u3093\u3088\u2661\u3010\u5927\u5bb6\u3061\u3072\u308d/Vtuber\u3011", "type": "vod", "user_video_play_history": null, "video_aggregate_info": {"id": 222598489, "number_of_comments": 0, "total_views": 3436}, "video_comment_setting": {"allow_comment_flg": true, "disp_main_comment_flg": true, "disp_number_of_comment_flg": true, "disp_number_of_views_flg": true, "disp_rightside_comment_flg": true}, "video_delivery_target": {"id": 2}, "video_free_periods": [], "video_media_type": {"id": 1, "status": "movie"}}, {"active_video_filename": {"id": 84938, "length": 3635, "video_filename_type": {"id": 1, "value": "vod_origin"}}, "content_code": "smQJkkAZAt7nxynZT7EEAJy3", "display_date": "2024-07-19 05:01:00", "live_finished_at": null, "released_at": "2024-07-19 05:01:00", "start_with_free_part_flg": false, "thumbnail_url": "https://cdn.nicochannel.jp/public_html/contents/video_pages/34855/thumbnail_path?time=1721365262", "title": "\u3010\u8033\u8210\u3081ASMR\u3011\u820c\u3067\u307b\u3050\u3059\u8033\u8210\u3081\u30de\u30c3\u30b5\u30fc\u30b8\u5e97\u2661\u3010\u5927\u5bb6\u3061\u3072\u308d/Vtuber\u3011", "type": "vod", "user_video_play_history": null, "video_aggregate_info": {"id": 222615677, "number_of_comments": 0, "total_views": 2109}, "video_comment_setting": {"allow_comment_flg": true, "disp_main_comment_flg": true, "disp_number_of_comment_flg": true, "disp_number_of_views_flg": true, "disp_rightside_comment_flg": true}, "video_delivery_target": {"id": 2}, "video_free_periods": [], "video_media_type": {"id": 1, "status": "movie"}}, {"active_video_filename": {"id": 84935, "length": 3715, "video_filename_type": {"id": 1, "value": "vod_origin"}}, "content_code": "smLukzUEPDiMXnZi5nxUUUqR", "display_date": "2024-07-19 04:59:40", "live_finished_at": null, "released_at": "2024-07-19 04:59:40", "start_with_free_part_flg": false, "thumbnail_url": "https://cdn.nicochannel.jp/public_html/contents/video_pages/34854/thumbnail_path?time=1721365182", "title": "\u3010\u8033\u8210\u3081\u5410\u606fonly\u3011\u606f\u9063\u3044\u3068\u820c\u306e\u52d5\u304d\u3067\u5fc3\u5730\u3088\u304f\u7720\u3063\u3061\u3083\u3044\u307e\u3057\u3087\u3046\u306d\u2661\u3010\u5927\u5bb6\u3061\u3072\u308d/Vtuber\u3011", "type": "vod", "user_video_play_history": null, "video_aggregate_info": {"id": 222266289, "number_of_comments": 0, "total_views": 1066}, "video_comment_setting": {"allow_comment_flg": true, "disp_main_comment_flg": true, "disp_number_of_comment_flg": true, "disp_number_of_views_flg": true, "disp_rightside_comment_flg": true}, "video_delivery_target": {"id": 2}, "video_free_periods": [], "video_media_type": {"id": 1, "status": "movie"}}, {"active_video_filename": {"id": 84933, "length": 3716, "video_filename_type": {"id": 1, "value": "vod_origin"}}, "content_code": "smZ7wsS3bkTmUF7EHwL3PZHp", "display_date": "2024-07-19 04:58:00", "live_finished_at": null, "released_at": "2024-07-19 04:58:00", "start_with_free_part_flg": false, "thumbnail_url": "https://cdn.nicochannel.jp/public_html/contents/video_pages/34853/thumbnail_path?time=1721365082", "title": "\u3010\u8033\u8210\u3081ASMR\u3011\u307b\u304b\u307b\u304b\u5410\u606f\u3067\u6e29\u3081\u3066\u3042\u3052\u307e\u3059\u306d\u2661\u3010\u5927\u5bb6\u3061\u3072\u308d/Vtuber\u3011", "type": "vod", "user_video_play_history": null, "video_aggregate_info": {"id": 222517060, "number_of_comments": 0, "total_views": 1277}, "video_comment_setting": {"allow_comment_flg": true, "disp_main_comment_flg": true, "disp_number_of_comment_flg": true, "disp_number_of_views_flg": true, "disp_rightside_comment_flg": true}, "video_delivery_target": {"id": 2}, "video_free_periods": [], "video_media_type": {"id": 1, "status": "movie"}}, {"active_video_filename": {"id": 84931, "length": 3683, "video_filename_type": {"id": 1, "value": "vod_origin"}}, "content_code": "sm53hRYXFnvKEGiLsFmz6CEP", "display_date": "2024-07-19 04:56:12", "live_finished_at": null, "released_at": "2024-07-19 04:56:12", "start_with_free_part_flg": false, "thumbnail_url": "https://cdn.nicochannel.jp/public_html/contents/video_pages/34852/thumbnail_path?time=1721364974", "title": "\u3010\u8033\u8210\u3081ASMR\u3011\u512a\u7518\u30dc\u30a4\u30b9\u306e\u304a\u59c9\u3055\u3093\u306b\u7518\u653b\u3081\u3055\u308c\u3066\u30a4\u304d\u307e\u305b\u3093\u304b\uff1f\u2661\u3010\u5927\u5bb6\u3061\u3072\u308d/Vtuber\u3011", "type": "vod", "user_video_play_history": null, "video_aggregate_info": {"id": 222286566, "number_of_comments": 0, "total_views": 815}, "video_comment_setting": {"allow_comment_flg": true, "disp_main_comment_flg": true, "disp_number_of_comment_flg": true, "disp_number_of_views_flg": true, "disp_rightside_comment_flg": true}, "video_delivery_target": {"id": 2}, "video_free_periods": [], "video_media_type": {"id": 1, "status": "movie"}}, {"active_video_filename": {"id": 84928, "length": 3343, "video_filename_type": {"id": 1, "value": "vod_origin"}}, "content_code": "sm6euPGzAQNuPNCbf98aeVkQ", "display_date": "2024-07-19 04:54:43", "live_finished_at": null, "released_at": "2024-07-19 04:54:43", "start_with_free_part_flg": false, "thumbnail_url": "https://cdn.nicochannel.jp/public_html/contents/video_pages/34851/thumbnail_path?time=1721364884", "title": "\u3010\u8033\u8210\u3081ASMR\u3011\u3044\u3064\u3082\u9811\u5f35\u3063\u3066\u308b\u541b\u306b\u2661\u30de\u30de\u304b\u3089\u306e\u3054\u8912\u7f8e\u8033\u8210\u3081\uff01\u3010\u5927\u5bb6\u3061\u3072\u308d/Vtuber\u3011", "type": "vod", "user_video_play_history": null, "video_aggregate_info": {"id": 223784018, "number_of_comments": 0, "total_views": 346}, "video_comment_setting": {"allow_comment_flg": true, "disp_main_comment_flg": true, "disp_number_of_comment_flg": true, "disp_number_of_views_flg": true, "disp_rightside_comment_flg": true}, "video_delivery_target": {"id": 2}, "video_free_periods": [], "video_media_type": {"id": 1, "status": "movie"}}, {"active_video_filename": {"id": 84926, "length": 3661, "video_filename_type": {"id": 1, "value": "vod_origin"}}, "content_code": "smHgqahYidbqQRQcuGWdU5w6", "display_date": "2024-07-19 04:53:06", "live_finished_at": null, "released_at": "2024-07-19 04:53:06", "start_with_free_part_flg": false, "thumbnail_url": "https://cdn.nicochannel.jp/public_html/contents/video_pages/34850/thumbnail_path?time=1721364787", "title": "\u3010\u8033\u8210\u3081ASMR\u3011\u512a\u3057\u304f\u3066\u7518\u3005\u306a\u304a\u59c9\u3055\u3093\u306e\u6c17\u6301\u3061\u30a4\u30a4\u7279\u8a13\u2661\u3010\u5927\u5bb6\u3061\u3072\u308d/Vtuber\u3011", "type": "vod", "user_video_play_history": null, "video_aggregate_info": {"id": 230427485, "number_of_comments": 0, "total_views": 646}, "video_comment_setting": {"allow_comment_flg": true, "disp_main_comment_flg": true, "disp_number_of_comment_flg": true, "disp_number_of_views_flg": true, "disp_rightside_comment_flg": true}, "video_delivery_target": {"id": 2}, "video_free_periods": [], "video_media_type": {"id": 1, "status": "movie"}}, {"active_video_filename": {"id": 84924, "length": 3069, "video_filename_type": {"id": 1, "value": "vod_origin"}}, "content_code": "smQDnLnEGy7fZBKoDf2N8Jo8", "display_date": "2024-07-19 04:51:48", "live_finished_at": null, "released_at": "2024-07-19 04:51:48", "start_with_free_part_flg": false, "thumbnail_url": "https://cdn.nicochannel.jp/public_html/contents/video_pages/34849/thumbnail_path?time=1721364709", "title": "\u3010\u8033\u8210\u3081ASMR\u3011\u3044\u308d\u3044\u308d\u6211\u6162\u51fa\u6765\u306a\u304f\u306a\u3063\u305f\u304a\u59c9\u3055\u3093\u306b\u52dd\u3066\u307e\u3059\u304b\uff1f\u2661\u3010\u5927\u5bb6\u3061\u3072\u308d/Vtuber\u3011", "type": "vod", "user_video_play_history": null, "video_aggregate_info": {"id": 222226508, "number_of_comments": 0, "total_views": 1360}, "video_comment_setting": {"allow_comment_flg": true, "disp_main_comment_flg": true, "disp_number_of_comment_flg": true, "disp_number_of_views_flg": true, "disp_rightside_comment_flg": true}, "video_delivery_target": {"id": 2}, "video_free_periods": [], "video_media_type": {"id": 1, "status": "movie"}}, {"active_video_filename": {"id": 84921, "length": 3012, "video_filename_type": {"id": 1, "value": "vod_origin"}}, "content_code": "sm7H9KqjrPbASpifXaCPfmtW", "display_date": "2024-07-19 04:50:06", "live_finished_at": null, "released_at": "2024-07-19 04:50:06", "start_with_free_part_flg": false, "thumbnail_url": "https://cdn.nicochannel.jp/public_html/contents/video_pages/34848/thumbnail_path?time=1721364607", "title": "\u3010\u8033\u304b\u304dASMR\u96d1\u8ac7\u3011\u6d74\u8863\u3067ASMR\u2661\u304a\u819d\u3067\u30ea\u30e9\u30c3\u30af\u30b9\u3057\u307e\u3057\u3087\u3046\u2661EarCleaning/\uadc0\uccad\uc18c\u3010\u5927\u5bb6\u3061\u3072\u308d/Vtuber\u3011", "type": "vod", "user_video_play_history": null, "video_aggregate_info": {"id": 235133805, "number_of_comments": 0, "total_views": 91}, "video_comment_setting": {"allow_comment_flg": true, "disp_main_comment_flg": true, "disp_number_of_comment_flg": true, "disp_number_of_views_flg": true, "disp_rightside_comment_flg": true}, "video_delivery_target": {"id": 2}, "video_free_periods": [], "video_media_type": {"id": 1, "status": "movie"}}, {"active_video_filename": {"id": 84920, "length": 3730, "video_filename_type": {"id": 1, "value": "vod_origin"}}, "content_code": "smF5TKcAXjEnM7d6h5W6W6kP", "display_date": "2024-07-19 04:48:30", "live_finished_at": null, "released_at": "2024-07-19 04:48:30", "start_with_free_part_flg": false, "thumbnail_url": "https://cdn.nicochannel.jp/public_html/contents/video_pages/34847/thumbnail_path?time=1721364511", "title": "\u3010\u8033\u8210\u3081ASMR\u3011\u672c\u5f53\u306f\u512a\u3057\u304f\u3057\u305f\u3044\u3093\u3067\u3059\u3088\uff1f\u2661\u3010\u5927\u5bb6\u3061\u3072\u308d/Vtuber\u3011", "type": "vod", "user_video_play_history": null, "video_aggregate_info": {"id": 231213421, "number_of_comments": 0, "total_views": 356}, "video_comment_setting": {"allow_comment_flg": true, "disp_main_comment_flg": true, "disp_number_of_comment_flg": true, "disp_number_of_views_flg": true, "disp_rightside_comment_flg": true}, "video_delivery_target": {"id": 2}, "video_free_periods": [], "video_media_type": {"id": 1, "status": "movie"}}, {"active_video_filename": {"id": 84918, "length": 3801, "video_filename_type": {"id": 1, "value": "vod_origin"}}, "content_code": "smQFrbskPvi6DtSDfgFY9qNy", "display_date": "2024-07-19 04:46:08", "live_finished_at": null, "released_at": "2024-07-19 04:46:08", "start_with_free_part_flg": false, "thumbnail_url": "https://cdn.nicochannel.jp/public_html/contents/video_pages/34846/thumbnail_path?time=1721364370", "title": "\u3010\u8033\u8210\u3081ASMR\u3011\u6587\u53e5\u8a00\u3044\u306a\u304c\u3089\u3082\u512a\u3057\u304f\u4e01\u5be7\u306b\u8033\u8210\u3081\u3057\u3066\u304f\u308c\u308b\u304a\u59c9\u3055\u3093\u2661\u3010\u5927\u5bb6\u3061\u3072\u308d/Vtuber\u3011", "type": "vod", "user_video_play_history": null, "video_aggregate_info": {"id": 222687604, "number_of_comments": 0, "total_views": 306}, "video_comment_setting": {"allow_comment_flg": true, "disp_main_comment_flg": true, "disp_number_of_comment_flg": true, "disp_number_of_views_flg": true, "disp_rightside_comment_flg": true}, "video_delivery_target": {"id": 2}, "video_free_periods": [], "video_media_type": {"id": 1, "status": "movie"}}, {"active_video_filename": {"id": 84915, "length": 3749, "video_filename_type": {"id": 1, "value": "vod_origin"}}, "content_code": "smSvEeggL24RrAVWL9nTXb5M", "display_date": "2024-07-19 04:41:28", "live_finished_at": null, "released_at": "2024-07-19 04:41:28", "start_with_free_part_flg": false, "thumbnail_url": "https://cdn.nicochannel.jp/public_html/contents/video_pages/34845/thumbnail_path?time=1721364089", "title": "\u3010\u8033\u8210\u3081ASMR\u3011\u3044\u3064\u3082\u9811\u5f35\u3063\u3066\u308b\u304b\u3089\u304a\u8033\u306b\u3054\u8912\u7f8e\u3042\u3052\u3088\u3046\u306d\u2661\u3010\u5927\u5bb6\u3061\u3072\u308d/Vtuber\u3011", "type": "vod", "user_video_play_history": null, "video_aggregate_info": {"id": 230449405, "number_of_comments": 0, "total_views": 190}, "video_comment_setting": {"allow_comment_flg": true, "disp_main_comment_flg": true, "disp_number_of_comment_flg": true, "disp_number_of_views_flg": true, "disp_rightside_comment_flg": true}, "video_delivery_target": {"id": 2}, "video_free_periods": [], "video_media_type": {"id": 1, "status": "movie"}}, {"active_video_filename": {"id": 84910, "length": 3681, "video_filename_type": {"id": 1, "value": "vod_origin"}}, "content_code": "smKMLybnfPCztza6BR8vFuHQ", "display_date": "2024-07-19 04:35:12", "live_finished_at": null, "released_at": "2024-07-19 04:35:12", "start_with_free_part_flg": false, "thumbnail_url": "https://cdn.nicochannel.jp/public_html/contents/video_pages/34843/thumbnail_path?time=1721363714", "title": "\u3010\u8033\u304b\u304dASMR\u3011\u30de\u30de\u306e\u304a\u819d\u306e\u4e0a\u3067\u307e\u3063\u305f\u308a\u7652\u3055\u308c\u8033\u304b\u304d\u2661\u3010\u5927\u5bb6\u3061\u3072\u308d/Vtuber\u3011", "type": "vod", "user_video_play_history": null, "video_aggregate_info": {"id": 255877528, "number_of_comments": 0, "total_views": 36}, "video_comment_setting": {"allow_comment_flg": true, "disp_main_comment_flg": true, "disp_number_of_comment_flg": true, "disp_number_of_views_flg": true, "disp_rightside_comment_flg": true}, "video_delivery_target": {"id": 2}, "video_free_periods": [], "video_media_type": {"id": 1, "status": "movie"}}, {"active_video_filename": {"id": 84907, "length": 3781, "video_filename_type": {"id": 1, "value": "vod_origin"}}, "content_code": "smiyviokLtNVTCLS4ABY8MYe", "display_date": "2024-07-19 04:31:08", "live_finished_at": null, "released_at": "2024-07-19 04:31:08", "start_with_free_part_flg": false, "thumbnail_url": "https://cdn.nicochannel.jp/public_html/contents/video_pages/34841/thumbnail_path?time=1721363470", "title": "\u3010\u8033\u8210\u3081ASMR\u3011\u6700\u5f8c\u307e\u3067\u6211\u6162\u2661\u7518\u3005\u304a\u59c9\u3055\u3093\u306f\u304a\u8033\u3067\u308f\u304b\u3089\u305b\u305f\u3044\uff01\u3010\u5927\u5bb6\u3061\u3072\u308d/Vtuber\u3011", "type": "vod", "user_video_play_history": null, "video_aggregate_info": {"id": 227287150, "number_of_comments": 0, "total_views": 452}, "video_comment_setting": {"allow_comment_flg": true, "disp_main_comment_flg": true, "disp_number_of_comment_flg": true, "disp_number_of_views_flg": true, "disp_rightside_comment_flg": true}, "video_delivery_target": {"id": 2}, "video_free_periods": [], "video_media_type": {"id": 1, "status": "movie"}}, {"active_video_filename": {"id": 84905, "length": 3557, "video_filename_type": {"id": 1, "value": "vod_origin"}}, "content_code": "smRWrBDtaxiCtuhFTXYTCjHr", "display_date": "2024-07-19 04:28:58", "live_finished_at": null, "released_at": "2024-07-19 04:28:58", "start_with_free_part_flg": false, "thumbnail_url": "https://cdn.nicochannel.jp/public_html/contents/video_pages/34840/thumbnail_path?time=1721363339", "title": "\u3010\u8033\u8210\u3081ASMR\u3011\u30c8\u30ed\u30c8\u30ed\u306b\u306a\u3063\u3066\u623b\u308c\u306a\u304f\u306a\u3063\u3061\u3083\u3046\u2661\u3010\u5927\u5bb6\u3061\u3072\u308d/Vtuber\u3011", "type": "vod", "user_video_play_history": null, "video_aggregate_info": {"id": 245058167, "number_of_comments": 0, "total_views": 117}, "video_comment_setting": {"allow_comment_flg": true, "disp_main_comment_flg": true, "disp_number_of_comment_flg": true, "disp_number_of_views_flg": true, "disp_rightside_comment_flg": true}, "video_delivery_target": {"id": 2}, "video_free_periods": [], "video_media_type": {"id": 1, "status": "movie"}}, {"active_video_filename": {"id": 84903, "length": 3961, "video_filename_type": {"id": 1, "value": "vod_origin"}}, "content_code": "smL5p5FjViYsAPtSXpbGjShU", "display_date": "2024-07-19 04:27:05", "live_finished_at": null, "released_at": "2024-07-19 04:27:05", "start_with_free_part_flg": false, "thumbnail_url": "https://cdn.nicochannel.jp/public_html/contents/video_pages/34839/thumbnail_path?time=1721363227", "title": "\u3010\u4e21\u8033\u56c1\u304dASMR/\u4e59\u6210\u306a\u3067\u3057\u3053\u3055\u3093\u3011\u7518\u3084\u304b\u3057\u4e0a\u624b\u306a\u512a\u3057\u3044\u304a\u59c9\u3055\u3093\u306b\u631f\u307e\u308c\u3066\u81f3\u798f\u306a\u6642\u9593\u3092\u904e\u3054\u3057\u3066\u3044\u304d\u307e\u305b\u3093\u304b\uff1f\u3010\u5927\u5bb6\u3061\u3072\u308d/Vtuber\u3011", "type": "vod", "user_video_play_history": null, "video_aggregate_info": {"id": 256136947, "number_of_comments": 0, "total_views": 60}, "video_comment_setting": {"allow_comment_flg": true, "disp_main_comment_flg": true, "disp_number_of_comment_flg": true, "disp_number_of_views_flg": true, "disp_rightside_comment_flg": true}, "video_delivery_target": {"id": 2}, "video_free_periods": [], "video_media_type": {"id": 1, "status": "movie"}}, {"active_video_filename": {"id": 84899, "length": 3840, "video_filename_type": {"id": 1, "value": "vod_origin"}}, "content_code": "sm4849R5nfqKvjpMTa8YLsSD", "display_date": "2024-07-19 04:24:39", "live_finished_at": null, "released_at": "2024-07-19 04:24:39", "start_with_free_part_flg": false, "thumbnail_url": "https://cdn.nicochannel.jp/public_html/contents/video_pages/34838/thumbnail_path?time=1721363080", "title": "\u3010\u8033\u8210\u3081ASMR\u3011(\u512a\u7518\u653b\u3081)\u52d5\u3044\u3061\u3083\u3060\uff5e\u3081\u2661\u305d\u308c\u304f\u3089\u3044\u3067\u304d\u307e\u3059\u3088\u306d\uff1f\u3010\u5927\u5bb6\u3061\u3072\u308d/Vtuber\u3011", "type": "vod", "user_video_play_history": null, "video_aggregate_info": {"id": 240411317, "number_of_comments": 0, "total_views": 243}, "video_comment_setting": {"allow_comment_flg": true, "disp_main_comment_flg": true, "disp_number_of_comment_flg": true, "disp_number_of_views_flg": true, "disp_rightside_comment_flg": true}, "video_delivery_target": {"id": 2}, "video_free_periods": [], "video_media_type": {"id": 1, "status": "movie"}}, {"active_video_filename": {"id": 84895, "length": 4053, "video_filename_type": {"id": 1, "value": "vod_origin"}}, "content_code": "smFTQpB3R2VWpew53JVrE35y", "display_date": "2024-07-19 04:20:23", "live_finished_at": null, "released_at": "2024-07-19 04:20:23", "start_with_free_part_flg": false, "thumbnail_url": "https://cdn.nicochannel.jp/public_html/contents/video_pages/34837/thumbnail_path?time=1721362825", "title": "\u3010\u8033\u8210\u3081ASMR\u3011\u512a\u3057\u304f\u3001\u305d\u3057\u3066\u7518\uff5e\u304f\u2661\u4e01\u5be7\u3067\u8569\u3051\u308b\u3088\u3046\u306a\u8033\u8210\u3081ASMR\u306f\u3044\u304b\u304c\u3067\u3059\u304b\uff1f\u3010\u5927\u5bb6\u3061\u3072\u308d/Vtuber\u6e96\u5099\u4e2d\u3011", "type": "vod", "user_video_play_history": null, "video_aggregate_info": {"id": 269318892, "number_of_comments": 0, "total_views": 85}, "video_comment_setting": {"allow_comment_flg": true, "disp_main_comment_flg": true, "disp_number_of_comment_flg": true, "disp_number_of_views_flg": true, "disp_rightside_comment_flg": true}, "video_delivery_target": {"id": 2}, "video_free_periods": [], "video_media_type": {"id": 1, "status": "movie"}}, {"active_video_filename": {"id": 84893, "length": 3967, "video_filename_type": {"id": 1, "value": "vod_origin"}}, "content_code": "smN2KJKB56PK9MpiXdSLpBMZ", "display_date": "2024-07-19 04:18:06", "live_finished_at": null, "released_at": "2024-07-19 04:18:06", "start_with_free_part_flg": false, "thumbnail_url": "https://cdn.nicochannel.jp/public_html/contents/video_pages/34836/thumbnail_path?time=1721362688", "title": "\u3010\u8033\u8210\u3081ASMR\u3011\u306d\u3063\u3068\u308a\u3057\u3064\u3053\u304f\u304a\u8033\u3092\u820c\u3067\u3044\u3058\u3081\u3089\u308c\u3066\u30a4\u304d\u307e\u305b\u3093\u304b\uff1f\u3010\u5927\u5bb6\u3061\u3072\u308d/Vtuber\u6e96\u5099\u4e2d\u3011", "type": "vod", "user_video_play_history": null, "video_aggregate_info": {"id": 233777775, "number_of_comments": 0, "total_views": 349}, "video_comment_setting": {"allow_comment_flg": true, "disp_main_comment_flg": true, "disp_number_of_comment_flg": true, "disp_number_of_views_flg": true, "disp_rightside_comment_flg": true}, "video_delivery_target": {"id": 2}, "video_free_periods": [], "video_media_type": {"id": 1, "status": "movie"}}, {"active_video_filename": {"id": 84885, "length": 3775, "video_filename_type": {"id": 1, "value": "vod_origin"}}, "content_code": "smWpDZHiZcJhveHXnKHemQUN", "display_date": "2024-07-19 04:00:08", "live_finished_at": null, "released_at": "2024-07-19 04:00:08", "start_with_free_part_flg": false, "thumbnail_url": "https://cdn.nicochannel.jp/public_html/contents/video_pages/34835/thumbnail_path?time=1721361609", "title": "\u3010\u56c1\u304d\u3042\u308a\u8033\u8210\u3081ASMR\u3011\u512a\u3057\u304f\u3055\u308c\u305f\u3044\uff1f\u610f\u5730\u60aa\u3055\u308c\u305f\u3044\uff1f\u3010\u5927\u5bb6\u3061\u3072\u308d/Vtuber\u6e96\u5099\u4e2d\u3011", "type": "vod", "user_video_play_history": null, "video_aggregate_info": {"id": 244041235, "number_of_comments": 0, "total_views": 236}, "video_comment_setting": {"allow_comment_flg": true, "disp_main_comment_flg": true, "disp_number_of_comment_flg": true, "disp_number_of_views_flg": true, "disp_rightside_comment_flg": true}, "video_delivery_target": {"id": 2}, "video_free_periods": [], "video_media_type": {"id": 1, "status": "movie"}}, {"active_video_filename": {"id": 84883, "length": 1488, "video_filename_type": {"id": 1, "value": "vod_origin"}}, "content_code": "smGhURrM2RkdA7Bhw4a2uMgG", "display_date": "2024-07-19 03:58:17", "live_finished_at": null, "released_at": "2024-07-19 03:58:17", "start_with_free_part_flg": false, "thumbnail_url": "https://cdn.nicochannel.jp/public_html/contents/video_pages/34834/thumbnail_path?time=1721361499", "title": "\u3010\u7761\u7720\u5c0e\u5165/\u65b0\u7f8e\u5357\u5409\u4f5c\u3000\u624b\u888b\u3092\u8cb7\u3044\u306b\u3011\u5927\u4eba\u306e\u305f\u3081\u306e\u8aad\u307f\u805e\u304b\u305b\u2661\u30de\u30de\u306e\u512a\u3057\u3044\u58f0\u3067\u304a\u3084\u3059\u307f\u306a\u3055\u3044\ud83c\udf19\u3010\u5927\u5bb6\u3061\u3072\u308d/Vtuber\u6e96\u5099\u4e2d\u3011", "type": "vod", "user_video_play_history": null, "video_aggregate_info": {"id": 379035125, "number_of_comments": 0, "total_views": 14}, "video_comment_setting": {"allow_comment_flg": true, "disp_main_comment_flg": true, "disp_number_of_comment_flg": true, "disp_number_of_views_flg": true, "disp_rightside_comment_flg": true}, "video_delivery_target": {"id": 2}, "video_free_periods": [], "video_media_type": {"id": 1, "status": "movie"}}, {"active_video_filename": {"id": 84880, "length": 2928, "video_filename_type": {"id": 1, "value": "vod_origin"}}, "content_code": "smPxzBuLgEBrLLeVnQAAi62P", "display_date": "2024-07-19 03:50:12", "live_finished_at": null, "released_at": "2024-07-19 03:50:12", "start_with_free_part_flg": false, "thumbnail_url": "https://cdn.nicochannel.jp/public_html/contents/video_pages/34832/thumbnail_path?time=1721361014", "title": "\u3010\u56c1\u304dASMR/3Dio\u767d\u3011\u7720\u6c17\u3092\u8a98\u3046\u30bc\u30ed\u8ddd\u96e2\u56c1\u304d\u3010\u5927\u5bb6\u3061\u3072\u308d/Vtuber\u6e96\u5099\u4e2d\u3011", "type": "vod", "user_video_play_history": null, "video_aggregate_info": {"id": 233409433, "number_of_comments": 0, "total_views": 21}, "video_comment_setting": {"allow_comment_flg": true, "disp_main_comment_flg": true, "disp_number_of_comment_flg": true, "disp_number_of_views_flg": true, "disp_rightside_comment_flg": true}, "video_delivery_target": {"id": 2}, "video_free_periods": [], "video_media_type": {"id": 1, "status": "movie"}}, {"active_video_filename": {"id": 84878, "length": 3863, "video_filename_type": {"id": 1, "value": "vod_origin"}}, "content_code": "smJsWHF7bbSiudfo3MPK2C47", "display_date": "2024-07-19 03:48:17", "live_finished_at": null, "released_at": "2024-07-19 03:48:17", "start_with_free_part_flg": false, "thumbnail_url": "https://cdn.nicochannel.jp/public_html/contents/video_pages/34831/thumbnail_path?time=1721360898", "title": "\u3010\u30b7\u30c1\u30e5\u30a8\u30fc\u30b7\u30e7\u30f3ASMR/\u8033\u8210\u3081\u3011\u6ede\u7d0d\u3057\u305f\u5206\u306f\u3042\u306a\u305f\u306e\u304a\u8033\u3067\u3057\u3063\u304b\u308a\u56de\u53ce\u3055\u305b\u3066\u3082\u3089\u3044\u307e\u3059\u306d\u2661\u3010\u5927\u5bb6\u3061\u3072\u308d/Vtuber\u6e96\u5099\u4e2d\u3011", "type": "vod", "user_video_play_history": null, "video_aggregate_info": {"id": 224204957, "number_of_comments": 0, "total_views": 422}, "video_comment_setting": {"allow_comment_flg": true, "disp_main_comment_flg": true, "disp_number_of_comment_flg": true, "disp_number_of_views_flg": true, "disp_rightside_comment_flg": true}, "video_delivery_target": {"id": 2}, "video_free_periods": [], "video_media_type": {"id": 1, "status": "movie"}}, {"active_video_filename": {"id": 84875, "length": 3689, "video_filename_type": {"id": 1, "value": "vod_origin"}}, "content_code": "smeND7gSFKNvPNE9NNsyJVmA", "display_date": "2024-07-19 03:44:58", "live_finished_at": null, "released_at": "2024-07-19 03:44:58", "start_with_free_part_flg": false, "thumbnail_url": "https://cdn.nicochannel.jp/public_html/contents/video_pages/34830/thumbnail_path?time=1721360700", "title": "\u3010\u8033\u304b\u304dASMR/\u767d\u8033\u3011\u5fc3\u5730\u3088\u3044\u632f\u52d5\u3067\u30de\u30c3\u30b5\u30fc\u30b8\u2661\u56c1\u304d\u58f0\u3068\u97f3\u53c9\u306e\u97f3\u3068\u632f\u52d5\u3067\u7652\u3055\u308c\u308bASMR\u3010\u5927\u5bb6\u3061\u3072\u308d/Vtuber\u6e96\u5099\u4e2d\u3011", "type": "vod", "user_video_play_history": null, "video_aggregate_info": {"id": 256131946, "number_of_comments": 0, "total_views": 17}, "video_comment_setting": {"allow_comment_flg": true, "disp_main_comment_flg": true, "disp_number_of_comment_flg": true, "disp_number_of_views_flg": true, "disp_rightside_comment_flg": true}, "video_delivery_target": {"id": 2}, "video_free_periods": [], "video_media_type": {"id": 1, "status": "movie"}}, {"active_video_filename": {"id": 84873, "length": 3204, "video_filename_type": {"id": 1, "value": "vod_origin"}}, "content_code": "smKFWbtNoCFP2xFPoE9EN84h", "display_date": "2024-07-19 03:42:33", "live_finished_at": null, "released_at": "2024-07-19 03:42:33", "start_with_free_part_flg": false, "thumbnail_url": "https://cdn.nicochannel.jp/public_html/contents/video_pages/34829/thumbnail_path?time=1721360555", "title": "\u3010ASMR\u3011\u304a\u75b2\u308c\u69d8\u3002\u512a\u3057\u3044\u58f0\u306b\u5305\u307e\u308c\u3066\u5fc3\u5730\u3088\u304f\u5bdd\u843d\u3061\u3057\u3061\u3083\u3044\u307e\u3057\u3087\u3046\u306d\u3002\u3010\u5927\u5bb6\u3061\u3072\u308d/Vtuber\u6e96\u5099\u4e2d\u3011", "type": "vod", "user_video_play_history": null, "video_aggregate_info": {"id": 255841243, "number_of_comments": 0, "total_views": 20}, "video_comment_setting": {"allow_comment_flg": true, "disp_main_comment_flg": true, "disp_number_of_comment_flg": true, "disp_number_of_views_flg": true, "disp_rightside_comment_flg": true}, "video_delivery_target": {"id": 2}, "video_free_periods": [], "video_media_type": {"id": 1, "status": "movie"}}, {"active_video_filename": {"id": 84871, "length": 3322, "video_filename_type": {"id": 1, "value": "vod_origin"}}, "content_code": "smmiev4LLAVJiRrpxmqsAoyX", "display_date": "2024-07-19 03:40:54", "live_finished_at": null, "released_at": "2024-07-19 03:40:54", "start_with_free_part_flg": false, "thumbnail_url": "https://cdn.nicochannel.jp/public_html/contents/video_pages/34828/thumbnail_path?time=1721360455", "title": "\u3010ASMR/\u96d1\u8ac7\u3011\u7720\u308c\u306a\u3044\u5b50\u304a\u3044\u3067\u2661\u304a\u3084\u3059\u307f\u306e\u524d\u306b\u6dfb\u3044\u5bdd\u3057\u306a\u304c\u3089\u5185\u7dd2\u2026\u3057\u307e\u3057\u3087\uff1f\u3010\u5927\u5bb6\u3061\u3072\u308d/Vtuber\u6e96\u5099\u4e2d\u3011", "type": "vod", "user_video_play_history": null, "video_aggregate_info": {"id": 368064816, "number_of_comments": 0, "total_views": 15}, "video_comment_setting": {"allow_comment_flg": true, "disp_main_comment_flg": true, "disp_number_of_comment_flg": true, "disp_number_of_views_flg": true, "disp_rightside_comment_flg": true}, "video_delivery_target": {"id": 2}, "video_free_periods": [], "video_media_type": {"id": 1, "status": "movie"}}, {"active_video_filename": {"id": 84869, "length": 3869, "video_filename_type": {"id": 1, "value": "vod_origin"}}, "content_code": "smhAKZVA9P5TqJriSZw2b42q", "display_date": "2024-07-19 03:37:59", "live_finished_at": null, "released_at": "2024-07-19 03:37:59", "start_with_free_part_flg": false, "thumbnail_url": "https://cdn.nicochannel.jp/public_html/contents/video_pages/34827/thumbnail_path?time=1721360280", "title": "\u3010\u8033\u8210\u3081ASMR\u3011\u8033\u8210\u3081\u7279\u5316\uff01\u97f3\u306b\u96c6\u4e2d\u3057\u3066\u30ea\u30e9\u30c3\u30af\u30b9\u3057\u3061\u3083\u3044\u307e\u3057\u3087\u3046\u2661\u3010\u5927\u5bb6\u3061\u3072\u308d/Vtuber\u6e96\u5099\u4e2d\u3011", "type": "vod", "user_video_play_history": null, "video_aggregate_info": {"id": 224308524, "number_of_comments": 0, "total_views": 156}, "video_comment_setting": {"allow_comment_flg": true, "disp_main_comment_flg": true, "disp_number_of_comment_flg": true, "disp_number_of_views_flg": true, "disp_rightside_comment_flg": true}, "video_delivery_target": {"id": 2}, "video_free_periods": [], "video_media_type": {"id": 1, "status": "movie"}}, {"active_video_filename": {"id": 84867, "length": 3883, "video_filename_type": {"id": 1, "value": "vod_origin"}}, "content_code": "sm4NVGVDciRej7TXiFun3MFM", "display_date": "2024-07-19 03:28:16", "live_finished_at": null, "released_at": "2024-07-19 03:28:16", "start_with_free_part_flg": false, "thumbnail_url": "https://cdn.nicochannel.jp/public_html/contents/video_pages/34826/thumbnail_path?time=1721359697", "title": "\u3010ASMR/\u8033\u8210\u3081\u3011\u512a\u3057\u304f\u3086\u3063\u304f\u308a\u4e01\u5be7\u306b\u304a\u8033\u3092\u8210\u3081\u3055\u305b\u3066\u304f\u3060\u3055\u3044\u2661Earlicking,\uadc0 \ud565\uae30,\u8214\u8033\u3010\u5927\u5bb6\u3061\u3072\u308d/Vtuber\u6e96\u5099\u4e2d\u3011", "type": "vod", "user_video_play_history": null, "video_aggregate_info": {"id": 224309459, "number_of_comments": 0, "total_views": 194}, "video_comment_setting": {"allow_comment_flg": true, "disp_main_comment_flg": true, "disp_number_of_comment_flg": true, "disp_number_of_views_flg": true, "disp_rightside_comment_flg": true}, "video_delivery_target": {"id": 2}, "video_free_periods": [], "video_media_type": {"id": 1, "status": "movie"}}, {"active_video_filename": {"id": 84865, "length": 3604, "video_filename_type": {"id": 1, "value": "vod_origin"}}, "content_code": "smiiARHHYgVcaRJcBnjgKB6U", "display_date": "2024-07-19 03:25:53", "live_finished_at": null, "released_at": "2024-07-19 03:25:53", "start_with_free_part_flg": false, "thumbnail_url": "https://cdn.nicochannel.jp/public_html/contents/video_pages/34825/thumbnail_path?time=1721359555", "title": "\u3010ASMR/\u7761\u7720\u5c0e\u5165\u3011\u30de\u30de\u304c\u6dfb\u3044\u5bdd\u3057\u3066\u5b50\u5b88\u6b4c\u3084\u7ae5\u8b21\u3092\u6b4c\u3063\u3066\u304f\u308c\u308b\u305d\u3046\u3067\u3059\u3010\u5927\u5bb6\u3061\u3072\u308d/Vtuber\u6e96\u5099\u4e2d\u3011", "type": "vod", "user_video_play_history": null, "video_aggregate_info": {"id": 257990626, "number_of_comments": 0, "total_views": 35}, "video_comment_setting": {"allow_comment_flg": true, "disp_main_comment_flg": true, "disp_number_of_comment_flg": true, "disp_number_of_views_flg": true, "disp_rightside_comment_flg": true}, "video_delivery_target": {"id": 2}, "video_free_periods": [], "video_media_type": {"id": 1, "status": "movie"}}, {"active_video_filename": {"id": 84863, "length": 3752, "video_filename_type": {"id": 1, "value": "vod_origin"}}, "content_code": "smUaHXKp6soHJ9t7K64C8h7s", "display_date": "2024-07-19 03:22:18", "live_finished_at": null, "released_at": "2024-07-19 03:22:18", "start_with_free_part_flg": false, "thumbnail_url": "https://cdn.nicochannel.jp/public_html/contents/video_pages/34824/thumbnail_path?time=1721359339", "title": "\u3010\u8033\u304b\u304d\u7df4\u7fd2ASMR\u3011\u6696\u7089\u306e\u97f3\u306b\u7652\u3055\u308c\u306a\u304c\u3089\u8033\u304b\u304d\u3068\u30de\u30c3\u30b5\u30fc\u30b8\u3067\u30c8\u30ed\u30c8\u30ed\u306b\u3057\u3061\u3083\u3044\u307e\u3059\u2661\u3010\u5927\u5bb6\u3061\u3072\u308d/Vtuber\u6e96\u5099\u4e2d\u3011", "type": "vod", "user_video_play_history": null, "video_aggregate_info": {"id": 257989719, "number_of_comments": 0, "total_views": 21}, "video_comment_setting": {"allow_comment_flg": true, "disp_main_comment_flg": true, "disp_number_of_comment_flg": true, "disp_number_of_views_flg": true, "disp_rightside_comment_flg": true}, "video_delivery_target": {"id": 2}, "video_free_periods": [], "video_media_type": {"id": 1, "status": "movie"}}, {"active_video_filename": {"id": 84861, "length": 3721, "video_filename_type": {"id": 1, "value": "vod_origin"}}, "content_code": "smePm4m7qdjFPdDZFCjAUnua", "display_date": "2024-07-19 03:15:29", "live_finished_at": null, "released_at": "2024-07-19 03:15:29", "start_with_free_part_flg": false, "thumbnail_url": "https://cdn.nicochannel.jp/public_html/contents/video_pages/34823/thumbnail_path?time=1721358930", "title": "\u3010\u8033\u8210\u3081ASMR/\u767d\u8033 3dio\u3011\u3042\u306a\u305f\u306e\u304a\u8033\u3068\u5fc3\u3092\u6e29\u3081\u3055\u305b\u3066\u2661\u3010\u5927\u5bb6\u3061\u3072\u308d\u3011", "type": "vod", "user_video_play_history": null, "video_aggregate_info": {"id": 226762868, "number_of_comments": 0, "total_views": 99}, "video_comment_setting": {"allow_comment_flg": true, "disp_main_comment_flg": true, "disp_number_of_comment_flg": true, "disp_number_of_views_flg": true, "disp_rightside_comment_flg": true}, "video_delivery_target": {"id": 2}, "video_free_periods": [], "video_media_type": {"id": 1, "status": "movie"}}]